satility/__init__.py
satility/downclass.py
satility/downloader.py
satility/downutils.py
satility/downwriter.py
satility/ensemble.py
satility/geoutils.py
satility/meta.py
satility/model.py
satility-0.0.3.dist-info/LICENSE
satility-0.0.3.dist-info/METADATA
satility-0.0.3.dist-info/WHEEL
satility-0.0.3.dist-info/RECORD
