Metadata-Version: 2.1
Name: satility
Version: 0.0.3
Summary: Utility to download and process SPOT-VGT and PROBA-V scenes via Terracatalogue
Home-page: https://github.com/IPL-UV/satility
Author: Julio Contreras
Author-email: contrerasnetk@gmail.com
Requires-Python: >=3.8,<4.0
Classifier: Programming Language :: Python :: 3
Classifier: Programming Language :: Python :: 3.8
Classifier: Programming Language :: Python :: 3.9
Classifier: Programming Language :: Python :: 3.10
Classifier: Programming Language :: Python :: 3.11
Classifier: Programming Language :: Python :: 3.12
Provides-Extra: torch
Requires-Dist: georeader-spaceml (>=1.2.8)
Requires-Dist: numpy (>=2.0.2)
Requires-Dist: rasterio (>=1.4.3)
Requires-Dist: segmentation-models-pytorch (>=0.5.0) ; extra == "torch"
Requires-Dist: terracatalogueclient (>=0.1.19)
Requires-Dist: torch (>=2.2) ; extra == "torch"
Requires-Dist: tqdm (>=4.66.1)
Project-URL: Documentation, https://github.com/IPL-UV/satility
Project-URL: Repository, https://github.com/IPL-UV/satility
